README.md
setup.py
timedeltaparser/__init__.py
timedeltaparser/_parser.py
timedeltaparser.egg-info/PKG-INFO
timedeltaparser.egg-info/SOURCES.txt
timedeltaparser.egg-info/dependency_links.txt
timedeltaparser.egg-info/top_level.txt