Metadata-Version: 1.0
Name: timedeltaparser
Version: 1.0.0
Summary: Parse a string that represents a timedelta
Home-page: http://www.angus.ai/
Author: Aurélien Moreau
Author-email: aurelien.moreau@angus.ai
License: Apache v2.0
Platform: UNKNOWN
